README.md
setup.cfg
setup.py
shoppon/__init__.py
shoppon.egg-info/PKG-INFO
shoppon.egg-info/SOURCES.txt
shoppon.egg-info/dependency_links.txt
shoppon.egg-info/entry_points.txt
shoppon.egg-info/not-zip-safe
shoppon.egg-info/top_level.txt
shoppon/api/__init__.py
shoppon/cmd/__init__.py
shoppon/cmd/api.py
shoppon/concurrency/__init__.py
shoppon/concurrency/monkey_patch.py
shoppon/config/__init__.py
shoppon/db/__init__.py
shoppon/db/mongo/__init__.py
shoppon/db/mongo/api.py
shoppon/db/sqlalchemy/__init__.py
shoppon/db/sqlalchemy/models.py
shoppon/logs/__init__.py
shoppon/logs/my_syslog.py
shoppon/spiders/__init__.py
shoppon/spiders/planning/__init__.py
shoppon/spiders/planning/main.py
shoppon/spiders/planning/pipline.py
shoppon/spiders/planning/settings.py
shoppon/tests/__init__.py
shoppon/tests/concurrency/__init__.py
shoppon/tests/concurrency/test_monkey_patch.py