Metadata-Version: 1.0
Name: shoppon
Version: 0.1.5
Summary: Demo code
Home-page: https://github.com/shoppon/shoppon/
Author: Shoppon
Author-email: shoppon@gmail.com
License: MIT
Platform: UNKNOWN
